simalign/__init__.py
simalign/simalign.py
simalign/utils.py
simalign-0.4.dist-info/LICENSE
simalign-0.4.dist-info/METADATA
simalign-0.4.dist-info/WHEEL
simalign-0.4.dist-info/top_level.txt
simalign-0.4.dist-info/RECORD
