Metadata-Version: 2.1
Name: simalign
Version: 0.4
Summary: Word Alignments using Pretrained Language Models
Home-page: https://github.com/cisnlp/simalign
Author: Masoud Jalili Sabet, Philipp Dufter
Author-email: philipp@cis.lmu.de,masoud@cis.lmu.de
Project-URL: Bug Tracker, https://github.com/cisnlp/simalign/issues
Keywords: NLP deep learning transformer pytorch BERT Word Alignment
Classifier: Programming Language :: Python :: 3
Classifier: License :: OSI Approved :: MIT License
Classifier: Operating System :: OS Independent
Requires-Python: >=3.6.0
License-File: LICENSE
Requires-Dist: numpy
Requires-Dist: torch
Requires-Dist: scipy
Requires-Dist: transformers
Requires-Dist: regex
Requires-Dist: networkx
Requires-Dist: scikit-learn
